{
	"templates": [{
			"code": "audit",
			"name": "Feature Audit",
			"description": "Analyze your current product and see which features are used",
			"target": {
				"workspace": "sales_demo",
				"card": "my_slug_insight"
			},
			"style": {
				"color": "green"
			},
			"categories": [
				"support"
			],
			"processes": [
				"monitor_sales"
			],
			"objectives": [
				"help_more"
			]
		}, {
			"code": "dev_test",
			"name": "Dev Test",
			"description": "Analyze your current product and see which features are used",
			"target": {
				"workspace": "atlassian_demo",
				"card": "copy_of_test"
			},
			"style": {
				"color": "green"
			},
			"categories": [
				"support"
			],
			"processes": [
				"monitor_sales"
			],
			"objectives": [
				"help_more"
			]
		}, {
			"code": "dev_fra",
			"name": "Check Francesco (workspace 20210326_trend_datacard)",
			"description": "Template for Francesco's tests",
			"target": {
				"workspace": "20210326_trend_datacard",
				"card": "sum_nuovi_positivi_denominazione_regione_8"
			},
			"style": {
				"color": "#add8e6"
			},
			"categories": [
				"support"
			],
			"processes": [
				"monitor_sales"
			],
			"objectives": [
				"help_more"
			]
		},
		{
			"code": "nps",
			"name": "NPS",
			"description": "This is NPS card with one line",
			"target": {
				"workspace": "sales_organization",
				"card": "nps_trend"
			},
			"style": {
				"color": "red"
			},
			"categories": [
				"sales"
			],
			"processes": [
				"monitor_sales"
			],
			"objectives": [
				"sell_more"
			]
		}
	],
	"categories": [{
			"code": "reccomended",
			"name": "Reccomended"
		},
		{
			"code": "sales_organization",
			"name": "Sales Organization"
		},
		{
			"code": "support",
			"name": "Support"
		},
		{
			"code": "product_and_cx",
			"name": "Product & CX"
		}, 
	       	{
			"code": "digital_marketing",
			"name": "Digital Marketing"
	      	}
	],
	"processes": [{
		"code": "monitor_sales",
		"name": "Monitor Sales"
	}],
	"objectives": [{
			"code": "sell_more",
			"name": "Sell more"
		},
		{
			"code": "help_more",
			"name": "Help more"
		}
	]
}
